accord/.gitignore
accord/__init__.py
accord/__init__.pyi
accord/_internal.cpython-311-x86_64-linux-gnu.so
accord/data/__init__.pyi
accord/data/indel.pyi
accord/data/stats.pyi
accord/py.typed
accord_rs-0.0.12.dist-info/METADATA
accord_rs-0.0.12.dist-info/WHEEL
accord_rs-0.0.12.dist-info/licenses/LICENSE
accord_rs-0.0.12.dist-info/RECORD
