Metadata-Version: 2.4
Name: accord-rs
Version: 0.0.12
Classifier: Development Status :: 3 - Alpha
Classifier: License :: OSI Approved :: MIT License
Classifier: Programming Language :: Rust
Classifier: Programming Language :: Python
License-File: LICENSE
Summary: Calculate consensus sequences
Author-email: Fynn Freyer <fynn.freyer@googlemail.com>
Requires-Python: >=3.8
Project-URL: Repository, https://github.com/FynnFreyer/accord-rs
Project-URL: Issues, https://github.com/FynnFreyer/accord-rs/issues
